formap/__init__.py
formap/__main__.py
formap/form_detector.py
formap/logger.py
formap/models/field.py
formap-0.1.1.dist-info/LICENSE
formap-0.1.1.dist-info/METADATA
formap-0.1.1.dist-info/WHEEL
formap-0.1.1.dist-info/RECORD
